{"Year":2018,"Games":[{"HomeResutl":0,"Played":false,"HomeTeam":"ewjdpo","GuestTeam":"wdhiod2","Day":1,"GuestResult":0},{"HomeResutl":0,"Played":false,"HomeTeam":"jfiew","GuestTeam":"jcdop","Day":1,"GuestResult":0},{"HomeResutl":0,"Played":false,"HomeTeam":"ieifjo","GuestTeam":"jopdp","Day":1,"GuestResult":0},{"HomeResutl":0,"Played":false,"HomeTeam":"jioep","GuestTeam":"rhioefieow","Day":2,"GuestResult":0},{"HomeResutl":0,"Played":false,"HomeTeam":"iofoeioe","GuestTeam":"ieifjo","Day":2,"GuestResult":0},{"HomeResutl":0,"Played":false,"HomeTeam":"jcdop","GuestTeam":"jopdp","Day":2,"GuestResult":0},{"HomeResutl":0,"Played":false,"HomeTeam":"rhioefieow","GuestTeam":"jfiew","Day":3,"GuestResult":0},{"HomeResutl":0,"Played":false,"HomeTeam":"ieifjo","GuestTeam":"jioep","Day":3,"GuestResult":0},{"HomeResutl":0,"Played":false,"HomeTeam":"jcdop","GuestTeam":"iofoeioe","Day":3,"GuestResult":0},{"HomeResutl":0,"Played":false,"HomeTeam":"ieifjo","GuestTeam":"rhioefieow","Day":4,"GuestResult":0},{"HomeResutl":0,"Played":false,"HomeTeam":"jfiew","GuestTeam":"jopdp","Day":4,"GuestResult":0},{"HomeResutl":0,"Played":false,"HomeTeam":"jioep","GuestTeam":"jcdop","Day":4,"GuestResult":0},{"HomeResutl":0,"Played":false,"HomeTeam":"rhioefieow","GuestTeam":"jopdp","Day":5,"GuestResult":0},{"HomeResutl":0,"Played":false,"HomeTeam":"jcdop","GuestTeam":"ieifjo","Day":5,"GuestResult":0},{"HomeResutl":0,"Played":false,"HomeTeam":"iofoeioe","GuestTeam":"jfiew","Day":5,"GuestResult":0},{"HomeResutl":0,"Played":false,"HomeTeam":"jcdop","GuestTeam":"rhioefieow","Day":6,"GuestResult":0},{"HomeResutl":0,"Played":false,"HomeTeam":"jopdp","GuestTeam":"iofoeioe","Day":6,"GuestResult":0},{"HomeResutl":0,"Played":false,"HomeTeam":"jfiew","GuestTeam":"jioep","Day":6,"GuestResult":0},{"HomeResutl":0,"Played":false,"HomeTeam":"rhioefieow","GuestTeam":"iofoeioe","Day":7,"GuestResult":0},{"HomeResutl":0,"Played":false,"HomeTeam":"jioep","GuestTeam":"jopdp","Day":7,"GuestResult":0},{"HomeResutl":0,"Played":false,"HomeTeam":"jfiew","GuestTeam":"ieifjo","Day":7,"GuestResult":0}]}